mpv_simpleserver/__init__.py
mpv_simpleserver/__main__.py
mpv_simpleserver/mpv_simpleserver/__init__.py
mpv_simpleserver/mpv_simpleserver/static/favicon.ico
mpv_simpleserver/mpv_simpleserver/static/w3.css
mpv_simpleserver/mpv_simpleserver/views/mpv_simpleserver/index.tpl
mpv_simpleserver/mpv_simpleserver/views/mpv_simpleserver/provider/files.tpl
mpv_simpleserver/mpv_simpleserver/views/mpv_simpleserver/provider/invidous.tpl
mpv_simpleserver-0.2.dist-info/LICENSE
mpv_simpleserver-0.2.dist-info/METADATA
mpv_simpleserver-0.2.dist-info/WHEEL
mpv_simpleserver-0.2.dist-info/entry_points.txt
mpv_simpleserver-0.2.dist-info/top_level.txt
mpv_simpleserver-0.2.dist-info/RECORD
