Metadata-Version: 2.1
Name: mpv-simpleserver
Version: 0.2
Summary: Web server for mpv
Home-page: https://github.com/devkral/mpv_simpleserver
Author: Alexander K.
Author-email: devkral@web.de
License: BSD-3
Download-URL: https://github.com/devkral/mpv_simpleserver/tarball/v0.2
Keywords: mpv,helper,tool
Platform: Platform Independent
Classifier: License :: OSI Approved :: BSD License
Classifier: Operating System :: POSIX
Classifier: Environment :: Console
Classifier: Development Status :: 5 - Production/Stable
Classifier: Intended Audience :: Education
Classifier: Intended Audience :: End Users/Desktop
Classifier: Programming Language :: Python :: 3
Classifier: Programming Language :: Python :: 3.5
Classifier: Programming Language :: Python :: 3.6
Classifier: Programming Language :: Python :: 3.7
Classifier: Programming Language :: Python :: 3.8
Classifier: Programming Language :: Python :: 3 :: Only
Classifier: Topic :: Internet
Classifier: Topic :: Multimedia
Classifier: Topic :: Multimedia :: Sound/Audio :: Players
Requires-Dist: bottle
